qamomile/core/__init__.py
qamomile/core/ansatz/__init__.py
qamomile/core/ansatz/efficient_su2.py
qamomile/core/bitssample.py
qamomile/core/circuit/__init__.py
qamomile/core/circuit/circuit.py
qamomile/core/circuit/drawer.py
qamomile/core/circuit/parameter.py
qamomile/core/converters/__init__.py
qamomile/core/converters/converter.py
qamomile/core/converters/fqaoa.py
qamomile/core/converters/qaoa.py
qamomile/core/converters/qrao/__init__.py
qamomile/core/converters/qrao/graph_coloring.py
qamomile/core/converters/qrao/qrao21.py
qamomile/core/converters/qrao/qrao31.py
qamomile/core/converters/qrao/qrao32.py
qamomile/core/converters/qrao/qrao_space_efficient.py
qamomile/core/converters/utils.py
qamomile/core/ising_qubo.py
qamomile/core/modeler/__init__.py
qamomile/core/modeler/hamiltonian_expr.py
qamomile/core/modeler/pauli_expr.py
qamomile/core/operator.py
qamomile/core/post_process/__init__.py
qamomile/core/post_process/local_search.py
qamomile/core/transpiler.py
qamomile/cudaq/__init__.py
qamomile/cudaq/exceptions.py
qamomile/cudaq/parameter_converter.py
qamomile/cudaq/transpiler.py
qamomile/pennylane/__init__.py
qamomile/pennylane/exceptions.py
qamomile/pennylane/transpiler.py
qamomile/qiskit/__init__.py
qamomile/qiskit/exceptions.py
qamomile/qiskit/parameter_converter.py
qamomile/qiskit/transpiler.py
qamomile/quri_parts/__init__.py
qamomile/quri_parts/exceptions.py
qamomile/quri_parts/parameter_converter.py
qamomile/quri_parts/transpiler.py
qamomile/qutip/__init__.py
qamomile/qutip/exceptions.py
qamomile/qutip/transpiler.py
qamomile/udm/__init__.py
qamomile/udm/copyline.py
qamomile/udm/core.py
qamomile/udm/mwis_solver.py
qamomile/udm/transpiler.py
qamomile/udm/utils.py
qamomile-0.8.0.dist-info/METADATA
qamomile-0.8.0.dist-info/WHEEL
qamomile-0.8.0.dist-info/RECORD
