Metadata-Version: 2.3
Name: qamomile
Version: 0.8.0
Summary: 
Author: Jij Inc.
Author-email: info@j-ij.com
Requires-Python: >=3.10,<3.13
Classifier: Programming Language :: Python :: 3
Classifier: Programming Language :: Python :: 3.10
Classifier: Programming Language :: Python :: 3.11
Classifier: Programming Language :: Python :: 3.12
Provides-Extra: cudaq
Provides-Extra: pennylane
Provides-Extra: qiskit
Provides-Extra: quri-parts
Provides-Extra: qutip
Requires-Dist: bloqade-analog (>=0.16.5)
Requires-Dist: cudaq (>=0.11.0,<0.12.0) ; (sys_platform == "linux") and (extra == "cudaq")
Requires-Dist: jijmodeling (>=1.12.3,<2.0.0)
Requires-Dist: matplotlib (>=3.9.2,<4.0.0)
Requires-Dist: ommx (>=2.0.2,<3.0.0)
Requires-Dist: pennylane (>=0.39.0,<0.40.0) ; extra == "pennylane"
Requires-Dist: qiskit (>=2.1.0,<3.0.0) ; extra == "qiskit"
Requires-Dist: quri-parts-circuit (>=0.19.0,<0.20.0)
Requires-Dist: quri-parts-core (>=0.19.0,<0.20.0)
Requires-Dist: quri-parts-qulacs[quri-parts] (>=0.19.0,<0.20.0) ; extra == "quri-parts"
Requires-Dist: qutip (>=5.0.4,<6.0.0) ; extra == "qutip"
